artifact/__init__.py
artifact/artifact_client.py
artifact/artifact_graph.py
artifact/utils.py
artifact/client/__init__.py
artifact/client/api_client.py
artifact/client/configuration.py
artifact/client/default_api.py
artifact/errors/__init__.py
artifact/errors/error.py
artifact/errors/exceptions.py
artifact/errors/graph_already_exists_error.py
artifact/errors/not_found_error.py
artifact/errors/service_error.py
artifact/errors/unauthorized_error.py
artifact/models/__init__.py
artifact/models/api_response.py
artifact/models/chat_history.py
artifact/models/chat_message.py
artifact/models/create_graph_request.py
artifact/models/delete_graph200_response.py
artifact/models/document_meta.py
artifact/models/graph.py
artifact/models/graph_edge.py
artifact/models/graph_node.py
artifact/models/graph_stats.py
artifact/models/index_config.py
artifact/models/ingest_document_request.py
artifact/models/invalid_request_error.py
artifact/models/invocation_breakdown.py
artifact/models/operation_log.py
artifact/models/organization.py
artifact/models/presign_request.py
artifact/models/presign_response.py
artifact/models/query_request.py
artifact/models/query_result.py
artifact/models/rest.py
artifact/models/search_type.py
artifact/models/submit_prompt_request.py
artifact/models/usage_report.py
artifact_client-2.4.5.dist-info/METADATA
artifact_client-2.4.5.dist-info/WHEEL
artifact_client-2.4.5.dist-info/licenses/LICENSE
artifact_client-2.4.5.dist-info/RECORD
