Metadata-Version: 2.3
Name: artifact-client
Version: 2.4.5
Summary: Python client for the Artifact API
Project-URL: Homepage, https://github.com/Ozone-App/artifact-python-client
Project-URL: Repository, https://github.com/Ozone-App/artifact-python-client
Author-email: Ozone Dev <ozone@ozone.tech>
License-Expression: Apache-2.0
License-File: LICENSE
Keywords: Artifact,Artifact Client API,GraphRAG,Ozone
Classifier: Intended Audience :: Developers
Classifier: License :: OSI Approved :: Apache Software License
Classifier: Operating System :: MacOS
Classifier: Operating System :: Microsoft :: Windows
Classifier: Operating System :: OS Independent
Classifier: Operating System :: POSIX
Classifier: Operating System :: POSIX :: Linux
Classifier: Programming Language :: Python :: 3.8
Classifier: Programming Language :: Python :: 3.9
Classifier: Programming Language :: Python :: 3.10
Classifier: Programming Language :: Python :: 3.11
Classifier: Programming Language :: Python :: 3.12
Classifier: Topic :: Software Development :: Libraries :: Python Modules
Requires-Python: >=3.8
Requires-Dist: certifi==2024.7.4
Requires-Dist: pydantic>=2
Requires-Dist: python-dateutil>=2.9.0
Requires-Dist: requests>=2.32.3
Requires-Dist: six==1.16.0
Requires-Dist: uri>=2.0.1
Requires-Dist: urllib3==2.2.2
